elkatip/__init__.py
elkatip/api.py
elkatip/elkatip.py
elkatip/gui.py
elkatip/storage/ui.png
elkatip/storage/uyghur-alphabet-map.json
elkatip/storage/uyghur-frinedly-list.json
elkatip/storage/uyghur-other-map.json
elkatip-1.0.1.dist-info/LICENSE
elkatip-1.0.1.dist-info/METADATA
elkatip-1.0.1.dist-info/WHEEL
elkatip-1.0.1.dist-info/top_level.txt
elkatip-1.0.1.dist-info/RECORD
