Metadata-Version: 2.1
Name: elkatip
Version: 1.0.1
Summary: Uighur string convert tool for gui
Home-page: https://github.com/kompasim/elkatip
Author: kompasim
Author-email: kompasim@163.com
License: MIT Licence
Keywords: uyghur,uighur,alkatip,elkatip,base,ext,convert,tool,gui
Platform: any
Classifier: Programming Language :: Python :: 3
Classifier: License :: OSI Approved :: MIT License
Classifier: Operating System :: OS Independent
